CHANGES.rst
LICENSE.rst
MANIFEST.in
README.rst
setup.cfg
setup.py
tox.ini
PySql_ORM.egg-info/PKG-INFO
PySql_ORM.egg-info/SOURCES.txt
PySql_ORM.egg-info/dependency_links.txt
PySql_ORM.egg-info/requires.txt
PySql_ORM.egg-info/top_level.txt
Pysql_ORM.egg-info/PKG-INFO
Pysql_ORM.egg-info/SOURCES.txt
Pysql_ORM.egg-info/dependency_links.txt
Pysql_ORM.egg-info/requires.txt
Pysql_ORM.egg-info/top_level.txt
pysql_orm/__init__.py
pysql_orm/_adapt.py
pysql_orm/_compat.py
pysql_orm/_langhelp.py
pysql_orm/_logger.py
pysql_orm/_signals.py
pysql_orm/exports.py
pysql_orm/model.py
pysql_orm/sa_help.py
pysql_orm/utils.py
pysql_orm/exts/__init__.py
pysql_orm/exts/co_field.py
pysql_orm/exts/co_table.py
pysql_orm/exts/column_types.py
pysql_orm/plugins/__init__.py
pysql_orm/plugins/_flask.py