Metadata-Version: 2.1
Name: PySql-ORM
Version: 2.5.8
Summary: Adapt SQLAlchemy ORM Support to web application, include Flask, Django, or any other web frameworks. A Fork GitRepo from: https://github.com/pallets/flask-sqlalchemy
Home-page: https://github.com/dodoru/pysql-orm
Author: Armin Ronacher
Author-email: armin.ronacher@active-4.com
Maintainer: dodoru
Maintainer-email: dodoru@foxmail.com
License: BSD-3-Clause
Classifier: Development Status :: 1 - Planning
Classifier: Environment :: Web Environment
Classifier: Intended Audience :: Developers
Classifier: License :: OSI Approved :: BSD License
Classifier: Operating System :: OS Independent
Classifier: Programming Language :: Python
Classifier: Programming Language :: Python :: 2
Classifier: Programming Language :: Python :: 2.7
Classifier: Programming Language :: Python :: 3
Classifier: Programming Language :: Python :: 3.4
Classifier: Programming Language :: Python :: 3.5
Classifier: Programming Language :: Python :: 3.6
Classifier: Programming Language :: Python :: 3.7
Classifier: Programming Language :: Python :: 3.8
Classifier: Programming Language :: Python :: 3.9
Classifier: Programming Language :: Python :: 3.10
Classifier: Programming Language :: Python :: Implementation :: CPython
Classifier: Programming Language :: Python :: Implementation :: PyPy
Classifier: Topic :: Utilities
Classifier: Topic :: Internet :: WWW/HTTP :: Dynamic Content
Classifier: Topic :: Software Development :: Libraries :: Python Modules
Requires-Python: >= 2.7, != 3.0.*, != 3.1.*, != 3.2.*, != 3.3.*
License-File: LICENSE.rst
